pb_model/__init__.py
pb_model/admin.py
pb_model/apps.py
pb_model/fields.py
pb_model/models.py
pb_model/urls.py
pb_model/views.py
pb_model/migrations/__init__.py
pb_model/static/README.md
pb_model/templates/base.html
pb_model/tests/__init__.py
pb_model/tests/models.py
pb_model/tests/models_pb2.py
pb_model/tests/tests.py
django_pb_model-0.3.3.dist-info/AUTHORS
django_pb_model-0.3.3.dist-info/LICENSE
django_pb_model-0.3.3.dist-info/METADATA
django_pb_model-0.3.3.dist-info/WHEEL
django_pb_model-0.3.3.dist-info/top_level.txt
django_pb_model-0.3.3.dist-info/RECORD
