Metadata-Version: 2.1
Name: django-pb-model
Version: 0.3.3
Summary: Protobuf mixin for Django model
Home-page: https://github.com/myyang/django-pb-model
Author: myyang
Author-email: ymy1019@gmail.com
License: MIT License
Platform: UNKNOWN
Classifier: Environment :: Web Environment
Classifier: Framework :: Django
Classifier: Intended Audience :: Developers
Classifier: License :: OSI Approved :: MIT License
Classifier: Operating System :: OS Independent
Classifier: Programming Language :: Python
Classifier: Programming Language :: Python :: 3
Classifier: Topic :: Internet :: WWW/HTTP
Classifier: Topic :: Internet :: WWW/HTTP :: Dynamic Content
License-File: LICENSE
License-File: AUTHORS
Requires-Dist: django (>=1.11)
Requires-Dist: protobuf (>=3.1)
